jupyterlab_lsf/__init__.py
jupyterlab_lsf/main.py
jupyterlab_lsf-0.1.2.dist-info/METADATA
jupyterlab_lsf-0.1.2.dist-info/WHEEL
jupyterlab_lsf-0.1.2.dist-info/entry_points.txt
jupyterlab_lsf-0.1.2.dist-info/top_level.txt
jupyterlab_lsf-0.1.2.dist-info/RECORD
